LICENSE
Makefile
README.md
VERSION
ez_setup.py
requirements.txt
setup.py
.idea/vcs.xml
docs/README.md
sfalearn/__init__.py
sfalearn/angluin_dfa.py
sfalearn/angluin_fst.py
sfalearn/angluin_sfa.py
sfalearn/observationtableinit.py
sfalearn.egg-info/PKG-INFO
sfalearn.egg-info/SOURCES.txt
sfalearn.egg-info/dependency_links.txt
sfalearn.egg-info/namespace_packages.txt
sfalearn.egg-info/not-zip-safe
sfalearn.egg-info/requires.txt
sfalearn.egg-info/top_level.txt
tests/README.md