Metadata-Version: 1.1
Name: sfalearn
Version: 0.0.5
Summary: Automata Learning
Home-page: https://github.com/GeorgeArgyros/sfalearn
Author: George Argyros, Ioannis Stais
Author-email: ioannis.stais@gmail.com
License: UNKNOWN
Download-URL: https://github.com/GeorgeArgyros/sfalearn/tarball/master
Platform: Any
Classifier: Development Status :: 3 - Alpha
Classifier: Programming Language :: Python
Classifier: Programming Language :: Python :: 2
Classifier: Programming Language :: Python :: 2.7
Classifier: Intended Audience :: Developers
Classifier: Environment :: Console
